linx_connection/__init__.py
linx_connection-0.0.2.dist-info/LICENSE.md
linx_connection-0.0.2.dist-info/METADATA
linx_connection-0.0.2.dist-info/WHEEL
linx_connection-0.0.2.dist-info/top_level.txt
linx_connection-0.0.2.dist-info/RECORD
