Metadata-Version: 2.1
Name: linx-connection
Version: 0.0.2
Summary: Module for talking to Arduino by serial port
Home-page: https://github.com/Mr-Andersen/LabWink
Author: Andrew Anderson
Author-email: andrew-anderson.neo@yandex.ru
License: GNU GPL
Platform: UNKNOWN
Classifier: Programming Language :: Python :: 3
Classifier: License :: OSI Approved :: GNU General Public License v3 or later (GPLv3+)
Classifier: Operating System :: OS Independent
Requires-Dist: pyserial
Requires-Dist: ruamel.yaml
